pa6e/__init__.py
pa6e-0.0.6.dist-info/METADATA
pa6e-0.0.6.dist-info/WHEEL
pa6e-0.0.6.dist-info/entry_points.txt
pa6e-0.0.6.dist-info/licenses/LICENSE
pa6e-0.0.6.dist-info/RECORD
