Metadata-Version: 2.3
Name: pa6e
Version: 0.0.6
Summary: tools to print to the PeriA6 bluetooth receipt printer
Requires-Python: >=3.13
Requires-Dist: pillow
Requires-Dist: pyobjc-core
Requires-Dist: pyobjc-framework-cocoa
Requires-Dist: pyobjc-framework-corebluetooth
Requires-Dist: pyobjc-framework-iobluetooth
Requires-Dist: tqdm
